python3_rocksdb/setup.py
python3_rocksdb/rocksdb/__init__.py
python3_rocksdb/rocksdb/errors.py
python3_rocksdb/rocksdb/interfaces.py
python3_rocksdb/rocksdb/merge_operators.py
python3_rocksdb/rocksdb/tests/__init__.py
python3_rocksdb/rocksdb/tests/test_db.py
python3_rocksdb/rocksdb/tests/test_memtable.py
python3_rocksdb/rocksdb/tests/test_options.py
python3_rocksdb-6.9.0.dist-info/LICENCE
python3_rocksdb-6.9.0.dist-info/METADATA
python3_rocksdb-6.9.0.dist-info/WHEEL
python3_rocksdb-6.9.0.dist-info/top_level.txt
python3_rocksdb-6.9.0.dist-info/RECORD
