Metadata-Version: 2.1
Name: python3_rocksdb
Version: 6.9.0
Summary: Python bindings for RocksDB
Author-email: Daniel Siegmann <dsiegmann@bluewin.ch>
Project-URL: Homepage, https://github.com/chainlaboratory/python-rocksdb
Classifier: Programming Language :: Python :: 3
Classifier: License :: OSI Approved :: MIT License
Classifier: Operating System :: OS Independent
Requires-Python: >=3.8
License-File: LICENCE
